skosprovider_rdf/__init__.py
skosprovider_rdf/providers.py
skosprovider_rdf/utils.py
skosprovider_rdf-1.4.0.dist-info/METADATA
skosprovider_rdf-1.4.0.dist-info/WHEEL
skosprovider_rdf-1.4.0.dist-info/licenses/LICENSE
skosprovider_rdf-1.4.0.dist-info/RECORD
