Metadata-Version: 2.4
Name: skosprovider_rdf
Version: 1.4.0
Summary: skosprovider_rdf
Project-URL: History, https://github.com/OnroerendErfgoed/skosprovider_rdf/blob/master/HISTORY.rst
Project-URL: Tracker, https://github.com/OnroerendErfgoed/skosprovider_rdf/issues
Project-URL: Source, https://github.com/OnroerendErfgoed/skosprovider_rdf
Project-URL: Documentation, https://skosprovider-rdf.readthedocs.io/en/latest/
Author-email: Flanders Heritage Agency <ict@onroerenderfgoed.be>
License-File: LICENSE
Keywords: rdf,skos,skosprovider,thesauri,vocabularies
Classifier: Development Status :: 5 - Production/Stable
Classifier: Framework :: Pyramid
Classifier: Programming Language :: Python
Classifier: Programming Language :: Python :: 3.10
Classifier: Programming Language :: Python :: 3.11
Classifier: Programming Language :: Python :: 3.12
Classifier: Programming Language :: Python :: 3.13
Classifier: Topic :: Internet :: WWW/HTTP
Classifier: Topic :: Internet :: WWW/HTTP :: WSGI :: Application
Requires-Python: <3.13.11,>=3.10
Requires-Dist: html5lib>=1.1
Requires-Dist: rdflib<7.0.0,>=6.2.0
Requires-Dist: skosprovider>=1.2.0
Provides-Extra: dev
Requires-Dist: coveralls>=4.0.1; extra == 'dev'
Requires-Dist: pytest-cov>=5.0.0; extra == 'dev'
Requires-Dist: pytest>=8.3.3; extra == 'dev'
